[
  {
    "userId": 12,
    "userInfos": {
      "firstName": "Karl",
      "lastName": "Dovineau",
      "age": 31
    },
    "score": [{ "value": 12, "fill": "#ff0000" }],
    "keyData": [
      {
        "kind": "calories",
        "value": "1,930",
        "unit": "kCal"
      },
      {
        "kind": "protéines",
        "value": 155,
        "unit": "g"
      },
      {
        "kind": "glucides",
        "value": 290,
        "unit": "g"
      },
      {
        "kind": "lipides",
        "value": 50,
        "unit": "g"
      }
    ],
    "activity": [
      {
        "day": "2020-07-01",
        "kg": 80,
        "cal": 240
      },
      {
        "day": "2020-07-02",
        "kg": 80,
        "cal": 220
      },
      {
        "day": "2020-07-03",
        "kg": 81,
        "cal": 280
      },
      {
        "day": "2020-07-04",
        "kg": 81,
        "cal": 290
      },
      {
        "day": "2020-07-05",
        "kg": 80,
        "cal": 160
      },
      {
        "day": "2020-07-06",
        "kg": 78,
        "cal": 162
      },
      {
        "day": "2020-07-07",
        "kg": 76,
        "cal": 390
      }
    ],
    "sessionsTiming": [
      {
        "day": 1,
        "sessionLength": 30
      },
      {
        "day": 2,
        "sessionLength": 23
      },
      {
        "day": 3,
        "sessionLength": 45
      },
      {
        "day": 4,
        "sessionLength": 50
      },
      {
        "day": 5,
        "sessionLength": 0
      },
      {
        "day": 6,
        "sessionLength": 0
      },
      {
        "day": 7,
        "sessionLength": 60
      }
    ],
    "performance": [
      {
        "kind": "Intensité",
        "value": 80
      },
      {
        "kind": "Vitesse",
        "value": 120
      },
      {
        "kind": "Force",
        "value": 140
      },
      {
        "kind": "Endurance",
        "value": 50
      },
      {
        "kind": "Energie",
        "value": 200
      },
      {
        "kind": "Cardio",
        "value": 90
      }
    ]
  }
]
